.gitignore
.pylintrc
.readthedocs.yml
CODE_OF_CONDUCT.md
LICENSE
README.rst
circuitpython_hmac.py
requirements.txt
setup.py
.github/workflows/build.yml
.github/workflows/release.yml
circuitpython_hmac.egg-info/PKG-INFO
circuitpython_hmac.egg-info/SOURCES.txt
circuitpython_hmac.egg-info/dependency_links.txt
circuitpython_hmac.egg-info/requires.txt
circuitpython_hmac.egg-info/top_level.txt
docs/api.rst
docs/conf.py
docs/examples.rst
docs/index.rst
docs/_static/favicon.ico
examples/hmac_simpletest.py