Metadata-Version: 2.1
Name: circuitpython-hmac
Version: 0.2.1
Summary: HMAC (Keyed-Hashing for Message Authentication) Python module. Implements the HMAC algorithm as described by RFC 2104.
Home-page: https://github.com/jimbobbennett/CircuitPython_HMAC
Author: Jim Bennett
Author-email: jim.bennett@microsoft.com
License: MIT
Keywords: adafruit blinka circuitpython micropython hmac hashing authentication message
Platform: UNKNOWN
Classifier: Development Status :: 3 - Alpha
Classifier: Intended Audience :: Developers
Classifier: Topic :: Software Development :: Libraries
Classifier: Topic :: System :: Hardware
Classifier: License :: OSI Approved :: MIT License
Classifier: Programming Language :: Python :: 3
Classifier: Programming Language :: Python :: 3.4
Classifier: Programming Language :: Python :: 3.5
